deluge/__init__.py
deluge/_libtorrent.py
deluge/argparserbase.py
deluge/bencode.py
deluge/common.py
deluge/component.py
deluge/config.py
deluge/configmanager.py
deluge/conftest.py
deluge/crypto_utils.py
deluge/decorators.py
deluge/error.py
deluge/event.py
deluge/httpdownloader.py
deluge/log.py
deluge/maketorrent.py
deluge/metafile.py
deluge/path_chooser_common.py
deluge/pluginmanagerbase.py
deluge/transfer.py
deluge/core/__init__.py
deluge/core/alertmanager.py
deluge/core/authmanager.py
deluge/core/core.py
deluge/core/daemon.py
deluge/core/daemon_entry.py
deluge/core/eventmanager.py
deluge/core/filtermanager.py
deluge/core/pluginmanager.py
deluge/core/preferencesmanager.py
deluge/core/rpcserver.py
deluge/core/torrent.py
deluge/core/torrentmanager.py
deluge/i18n/__init__.py
deluge/i18n/languages.py
deluge/i18n/util.py
deluge/i18n/ab/LC_MESSAGES/deluge.mo
deluge/i18n/af/LC_MESSAGES/deluge.mo
deluge/i18n/ar/LC_MESSAGES/deluge.mo
deluge/i18n/ast/LC_MESSAGES/deluge.mo
deluge/i18n/be/LC_MESSAGES/deluge.mo
deluge/i18n/bg/LC_MESSAGES/deluge.mo
deluge/i18n/bn/LC_MESSAGES/deluge.mo
deluge/i18n/bs/LC_MESSAGES/deluge.mo
deluge/i18n/ca/LC_MESSAGES/deluge.mo
deluge/i18n/cs/LC_MESSAGES/deluge.mo
deluge/i18n/cy/LC_MESSAGES/deluge.mo
deluge/i18n/da/LC_MESSAGES/deluge.mo
deluge/i18n/de/LC_MESSAGES/deluge.mo
deluge/i18n/el/LC_MESSAGES/deluge.mo
deluge/i18n/en_AU/LC_MESSAGES/deluge.mo
deluge/i18n/en_CA/LC_MESSAGES/deluge.mo
deluge/i18n/en_GB/LC_MESSAGES/deluge.mo
deluge/i18n/eo/LC_MESSAGES/deluge.mo
deluge/i18n/es/LC_MESSAGES/deluge.mo
deluge/i18n/et/LC_MESSAGES/deluge.mo
deluge/i18n/eu/LC_MESSAGES/deluge.mo
deluge/i18n/fa/LC_MESSAGES/deluge.mo
deluge/i18n/fi/LC_MESSAGES/deluge.mo
deluge/i18n/fo/LC_MESSAGES/deluge.mo
deluge/i18n/fr/LC_MESSAGES/deluge.mo
deluge/i18n/fy/LC_MESSAGES/deluge.mo
deluge/i18n/ga/LC_MESSAGES/deluge.mo
deluge/i18n/gl/LC_MESSAGES/deluge.mo
deluge/i18n/he/LC_MESSAGES/deluge.mo
deluge/i18n/hi/LC_MESSAGES/deluge.mo
deluge/i18n/hr/LC_MESSAGES/deluge.mo
deluge-2.2.0.dist-info/AUTHORS
deluge-2.2.0.dist-info/LICENSE
deluge-2.2.0.dist-info/METADATA
deluge-2.2.0.dist-info/WHEEL
deluge-2.2.0.dist-info/entry_points.txt
deluge-2.2.0.dist-info/top_level.txt
deluge-2.2.0.dist-info/RECORD
