Metadata-Version: 2.2
Name: deluge
Version: 2.2.0
Summary: BitTorrent Client
Home-page: https://deluge-torrent.org
Author: Deluge Team
Maintainer: Calum Lind
Maintainer-email: calumlind+deluge@gmail.com
License: GPLv3+
Project-URL: GitHub (mirror), https://github.com/deluge-torrent/deluge
Project-URL: Sourcecode, http://git.deluge-torrent.org/deluge
Project-URL: Issues, https://dev.deluge-torrent.org/report/1
Project-URL: Discussion, https://forum.deluge-torrent.org
Project-URL: Documentation, https://deluge.readthedocs.io
Keywords: torrent bittorrent p2p fileshare filesharing
Classifier: Development Status :: 4 - Beta
Classifier: Environment :: Console
Classifier: Environment :: Web Environment
Classifier: Environment :: X11 Applications :: GTK
Classifier: Framework :: Twisted
Classifier: Intended Audience :: End Users/Desktop
Classifier: License :: OSI Approved :: GNU General Public License v3 or later (GPLv3+)
Classifier: Programming Language :: Python
Classifier: Operating System :: MacOS :: MacOS X
Classifier: Operating System :: Microsoft :: Windows
Classifier: Operating System :: POSIX
Classifier: Topic :: Internet
Requires-Python: >=3.6
License-File: LICENSE
License-File: AUTHORS
Requires-Dist: twisted[tls]>=17.1
Requires-Dist: pyasn1
Requires-Dist: rencode
Requires-Dist: pyopenssl
Requires-Dist: pyxdg
Requires-Dist: mako
Requires-Dist: setuptools
Requires-Dist: pywin32; sys_platform == "win32"
Requires-Dist: certifi; sys_platform == "win32"
Requires-Dist: zope.interface
Provides-Extra: all
Requires-Dist: setproctitle; extra == "all"
Requires-Dist: pillow; extra == "all"
Requires-Dist: chardet; extra == "all"
Requires-Dist: ifaddr; extra == "all"
Dynamic: author
Dynamic: classifier
Dynamic: description
Dynamic: description-content-type
Dynamic: home-page
Dynamic: keywords
Dynamic: license
Dynamic: maintainer
Dynamic: maintainer-email
Dynamic: project-url
Dynamic: provides-extra
Dynamic: requires-dist
Dynamic: requires-python
Dynamic: summary
